[
  {
    "addr": "6raznvsRtEJWJvpi5dPco7uM6JYRvrxnpxKQmBcngFo",
    "sym": "$MESSI",
    "dex": "pumpswap",
    "score": 77,
    "alerted_at": "2026-06-22T14:26:40",
    "entry": 5.786e-05,
    "mcap": 57870.0,
    "vol1h": 119756.3,
    "ch1h": 110.0,
    "buy_pct": 64,
    "age_m": 77,
    "holder": null,
    "url": "https://dexscreener.com/solana/hl8pfju4wabmajzvkjeaoetzulnj1skyefswdsidemrs",
    "outcome": "stop",
    "outcome_pct": -55.3,
    "outcome_at": "2026-06-22T14:34:15",
    "elapsed_min": 7
  },
  {
    "addr": "25esJoEHNoHzR4GC8pBvGC2yuhauG71p4jnAp2Y4pump",
    "sym": "MKAIR",
    "dex": "pumpswap",
    "score": 76,
    "alerted_at": "2026-06-22T14:28:03",
    "entry": 5.288e-05,
    "mcap": 52880.0,
    "vol1h": 33961.52,
    "ch1h": 48.09,
    "buy_pct": 68,
    "age_m": 2,
    "holder": null,
    "url": "https://dexscreener.com/solana/fcxkbpdn1qpilnxarwwmfnqm9ivyryey5mmavvugcvnm",
    "outcome": "stop",
    "outcome_pct": -43.6,
    "outcome_at": "2026-06-22T14:28:47",
    "elapsed_min": 0
  },
  {
    "addr": "2jbA4D1YSPnH9beyUCPQSBhHqaDhbix8HYYrWQokpump",
    "sym": "UPPY",
    "dex": "pumpswap",
    "score": 87,
    "alerted_at": "2026-06-22T14:59:03",
    "entry": 5.036e-05,
    "mcap": 50347.0,
    "vol1h": 30812.12,
    "ch1h": 66.67,
    "buy_pct": 75,
    "age_m": 20,
    "holder": null,
    "url": "https://dexscreener.com/solana/axj9bnpyhq3mc1frscn2e7xengatbuajvbydmpztxlsf",
    "outcome": "+100%",
    "outcome_pct": 100.0,
    "outcome_at": "2026-06-22T20:17:07",
    "elapsed_min": 318,
    "targets_hit": [
      100
    ]
  },
  {
    "addr": "DRuiWiackJbKAgHt771ytXDeFrjC8Tab7FwH4Q8upump",
    "sym": "RIDDANCE",
    "dex": "pumpswap",
    "score": 75,
    "alerted_at": "2026-06-22T15:05:29",
    "entry": 0.0002966,
    "mcap": 296638.0,
    "vol1h": 550801.61,
    "ch1h": 155.0,
    "buy_pct": 79,
    "age_m": 61,
    "holder": null,
    "url": "https://dexscreener.com/solana/beuy7xnejuxznmjg1apftveulmpkekdcrymmpknldcky",
    "outcome": "stop",
    "outcome_pct": -36.1,
    "outcome_at": "2026-06-22T16:03:13",
    "elapsed_min": 57
  },
  {
    "addr": "CBm9mTzaL6EjkdhbHbz3t2SaA3odiqZKaPBVGw4kpump",
    "sym": "Smope",
    "dex": "pumpswap",
    "score": 85,
    "alerted_at": "2026-06-22T15:36:22",
    "entry": 0.000148,
    "mcap": 148030.0,
    "vol1h": 72511.44,
    "ch1h": 308.0,
    "buy_pct": 64,
    "age_m": 2,
    "holder": null,
    "url": "https://dexscreener.com/solana/7zxr8ubbvi6wc8yta8z4nthcjy2ifmnwopwk4svzy7sy",
    "outcome": "stop",
    "outcome_pct": -43.9,
    "outcome_at": "2026-06-22T16:28:29",
    "elapsed_min": 52
  },
  {
    "addr": "9wzLSP54t3TGGAAKjEBGrNMigzmxwj1N9S8RhFRbpump",
    "sym": "LUCIA",
    "dex": "pumpswap",
    "score": 75,
    "alerted_at": "2026-06-22T15:49:17",
    "entry": 0.0001075,
    "mcap": 107580.0,
    "vol1h": 43477.37,
    "ch1h": 83.65,
    "buy_pct": 79,
    "age_m": 8,
    "holder": null,
    "url": "https://dexscreener.com/solana/7xgyztgrxtzlzmo59jvwrnjvckyslgjb26vajqnfnxft",
    "outcome": "stop",
    "outcome_pct": -98.5,
    "outcome_at": "2026-06-22T17:25:46",
    "elapsed_min": 96
  },
  {
    "addr": "GfyGvcGGHGdYVjhf6BrF6Q99Bxdv6bpyQj9br2EZ7oKh",
    "sym": "NOTHING",
    "dex": "pumpswap",
    "score": 83,
    "alerted_at": "2026-06-22T16:42:31",
    "entry": 5.751e-05,
    "mcap": 57514.0,
    "vol1h": 30904.37,
    "ch1h": 734.0,
    "buy_pct": 83,
    "age_m": 2,
    "holder": null,
    "url": "https://dexscreener.com/solana/8uaqfpeamcg7ybzqgttq6n2whnvkmnvnagr8ag9l4cga",
    "outcome": "stop",
    "outcome_pct": -51.6,
    "outcome_at": "2026-06-22T16:47:51",
    "elapsed_min": 5
  },
  {
    "addr": "DpZXGc5E8cMPvbP8Mpcw54DfUJ2oeok5Td4gaEo5REi5",
    "sym": "CBN",
    "dex": "pumpswap",
    "score": 82,
    "alerted_at": "2026-06-22T16:51:23",
    "entry": 6.028e-05,
    "mcap": 60287.0,
    "vol1h": 5898.44,
    "ch1h": 106.0,
    "buy_pct": 75,
    "age_m": 1,
    "holder": null,
    "url": "https://dexscreener.com/solana/fbjww8k1s9folfgdqvmwy8n2gd7jvyhust5hjh8f7kuq",
    "outcome": "+100%",
    "outcome_pct": 106.0,
    "outcome_at": "2026-06-22T20:17:08",
    "elapsed_min": 205,
    "targets_hit": [
      100
    ]
  },
  {
    "addr": "2LjdJ1V7QBYYAnkLa8uFbdrrkKsvTAsqoXGRnS9mpump",
    "sym": "LSP",
    "dex": "pumpswap",
    "score": 87,
    "alerted_at": "2026-06-22T17:09:07",
    "entry": 5.172e-05,
    "mcap": 51730.0,
    "vol1h": 41123.12,
    "ch1h": 51.09,
    "buy_pct": 66,
    "age_m": 2,
    "holder": null,
    "url": "https://dexscreener.com/solana/fpdm84eubvr8cjxp9ucmcqh5ovq35fkggcermpmgwnsd",
    "outcome": "+100%",
    "outcome_pct": 128.0,
    "outcome_at": "2026-06-22T20:17:08",
    "elapsed_min": 187,
    "targets_hit": [
      100
    ]
  },
  {
    "addr": "GsBaMkqpR2u6Pmpbk5MecS2x9HuZQot8hGC86Psypump",
    "sym": " Ro Khanna",
    "dex": "pumpswap",
    "score": 100,
    "alerted_at": "2026-06-22T17:14:12",
    "entry": 0.0001064,
    "mcap": 106438.0,
    "vol1h": 61190.92,
    "ch1h": 110.0,
    "buy_pct": 81,
    "age_m": 2,
    "holder": null,
    "url": "https://dexscreener.com/solana/9nb5wrumugwkjxalebugzosx1fmcwee4745pnjcivp68",
    "outcome": "stop",
    "outcome_pct": -38.6,
    "outcome_at": "2026-06-22T17:23:36",
    "elapsed_min": 9
  },
  {
    "addr": "7z6Kw5mX5Kt7NBgqeW8xYNa4Kr6neRJok2UCZjuMpump",
    "sym": "VCSOL",
    "dex": "pumpswap",
    "score": 84,
    "alerted_at": "2026-06-22T18:09:44",
    "entry": 0.0001204,
    "mcap": 120440.0,
    "vol1h": 14238.53,
    "ch1h": 100.0,
    "buy_pct": 81,
    "age_m": 2,
    "holder": null,
    "url": "https://dexscreener.com/solana/3l789e8eqxlczpqstxhy45lubt17rggkzk7jjdfhxugn",
    "outcome": "expired",
    "outcome_pct": 50.3,
    "outcome_at": "2026-06-22T20:09:53",
    "elapsed_min": 120
  },
  {
    "addr": "6YqsppC6qjJ3Efgwt6wMef6YGDofAPzEP5egvdzvpump",
    "sym": "TrumpLoner",
    "dex": "pumpswap",
    "score": 72,
    "alerted_at": "2026-06-22T18:12:29",
    "entry": 0.0002111,
    "mcap": 211194.0,
    "vol1h": 13054.21,
    "ch1h": 166.0,
    "buy_pct": 75,
    "age_m": 3,
    "holder": null,
    "url": "https://dexscreener.com/solana/7ogyliljzuqrqojyrlfrzv8obdgdpuxzydkts61cdfkp",
    "outcome": "expired",
    "outcome_pct": 18.2,
    "outcome_at": "2026-06-22T20:12:38",
    "elapsed_min": 120
  },
  {
    "addr": "GFziLKWd2JX7XpzGMCL5fpWZfZ2DnbCraPkTkF5upump",
    "sym": "UFOBEAT",
    "dex": "pumpswap",
    "score": 83,
    "alerted_at": "2026-06-22T18:47:07",
    "entry": 5.822e-05,
    "mcap": 58224.0,
    "vol1h": 36551.93,
    "ch1h": 90.35,
    "buy_pct": 64,
    "age_m": 3,
    "holder": null,
    "url": "https://dexscreener.com/solana/2ahfcdyezjbmxrtbe8zdyu4k88dbe4dohfbakx6zx8nt",
    "outcome": "+100%",
    "outcome_pct": 147.3,
    "outcome_at": "2026-06-22T20:23:52",
    "elapsed_min": 96,
    "targets_hit": [
      200,
      100
    ]
  },
  {
    "addr": "4BMXS7ustoUu2efhB3T1FKEaDUzJHkLusxENDCSJpump",
    "sym": "BLACKCONDOR",
    "dex": "pumpswap",
    "score": 79,
    "alerted_at": "2026-06-22T20:17:13",
    "entry": 8.831e-05,
    "mcap": 88314.0,
    "vol1h": 178906.87,
    "ch1h": 43.78,
    "buy_pct": 82,
    "age_m": 33,
    "holder": null,
    "url": "https://dexscreener.com/solana/b9t1yo3xakq8y1wteydbzizq87q4gjyomkumaj8ymfy",
    "outcome": null,
    "outcome_pct": null,
    "outcome_at": null,
    "elapsed_min": null,
    "targets_hit": []
  },
  {
    "addr": "7WrfeDEmRS6mVfLd28BuHbpqV2WVFyECWjFJo3Lwpump",
    "sym": "Robber",
    "dex": "pumpswap",
    "score": 90,
    "alerted_at": "2026-06-22T20:22:10",
    "entry": 7.457e-05,
    "mcap": 74580.0,
    "vol1h": 181925.38,
    "ch1h": 70.81,
    "buy_pct": 80,
    "age_m": 6,
    "holder": null,
    "url": "https://dexscreener.com/solana/bf6vawblshptvaxoawhs2n4rxd9txrpfgcjmqtdz9deb",
    "outcome": "stop",
    "outcome_pct": -39.0,
    "outcome_at": "2026-06-22T20:22:54",
    "elapsed_min": 0,
    "targets_hit": []
  }
]